LICENSE
MANIFEST.in
README.rst
setup.cfg
setup.py
gapic_google_logging_v2.egg-info/PKG-INFO
gapic_google_logging_v2.egg-info/SOURCES.txt
gapic_google_logging_v2.egg-info/dependency_links.txt
gapic_google_logging_v2.egg-info/namespace_packages.txt
gapic_google_logging_v2.egg-info/requires.txt
gapic_google_logging_v2.egg-info/top_level.txt
google/__init__.py
google/__init__.pyc
google/cloud/__init__.py
google/cloud/__init__.pyc
google/cloud/gapic/__init__.py
google/cloud/gapic/logging/__init__.py
google/cloud/gapic/logging/v2/__init__.py
google/cloud/gapic/logging/v2/config_service_v2_api.py
google/cloud/gapic/logging/v2/config_service_v2_client_config.json
google/cloud/gapic/logging/v2/enums.py
google/cloud/gapic/logging/v2/logging_service_v2_api.py
google/cloud/gapic/logging/v2/logging_service_v2_client_config.json
google/cloud/gapic/logging/v2/metrics_service_v2_api.py
google/cloud/gapic/logging/v2/metrics_service_v2_client_config.json